goalsdata/__init__.py
goalsdata/load_data.py
GOALSData-1.0.0.dist-info/LICENSE
GOALSData-1.0.0.dist-info/METADATA
GOALSData-1.0.0.dist-info/WHEEL
GOALSData-1.0.0.dist-info/top_level.txt
GOALSData-1.0.0.dist-info/RECORD
