Metadata-Version: 2.1
Name: GOALSData
Version: 1.0.0
Summary: The GOALS package facilitates game outcome analysis using statistical learning techniques. It is designed for modeling and predicting football match results based on various statistical features.
Home-page: https://github.com/salvnetto/GOALS
Maintainer: Salvador Netto
Maintainer-email: salvv.netto@gmail.com
License: MIT
Project-URL: Bug Tracker, https://github.com/salvnetto/GOALS/issues
Project-URL: Source Code, https://github.com/salvnetto/GOALS
Platform: any
Classifier: Development Status :: 5 - Production/Stable
Classifier: Intended Audience :: Science/Research
Classifier: License :: OSI Approved :: MIT License
Classifier: Operating System :: OS Independent
Classifier: Programming Language :: Python
Classifier: Topic :: Database
Classifier: Topic :: Internet
Requires-Python: >3.5
License-File: LICENSE
Requires-Dist: pandas
